models/__init__.py
models/deepvar/__init__.py
models/etsformer/__init__.py
models/etsformer/estimator.py
models/etsformer/lightning_module.py
models/etsformer/model.py
models/etsformer/module.py
gluonts_extend-1.0.1.dist-info/LICENSE
gluonts_extend-1.0.1.dist-info/METADATA
gluonts_extend-1.0.1.dist-info/WHEEL
gluonts_extend-1.0.1.dist-info/top_level.txt
gluonts_extend-1.0.1.dist-info/RECORD
